COPYING
MANIFEST.in
README.rst
buildout.cfg
develop.cfg
pyproject.toml
requirements.txt
setup.py
version.txt
bob/__init__.py
bob.learn.pytorch.egg-info/PKG-INFO
bob.learn.pytorch.egg-info/SOURCES.txt
bob.learn.pytorch.egg-info/dependency_links.txt
bob.learn.pytorch.egg-info/entry_points.txt
bob.learn.pytorch.egg-info/not-zip-safe
bob.learn.pytorch.egg-info/requires.txt
bob.learn.pytorch.egg-info/top_level.txt
bob/learn/__init__.py
bob/learn/pytorch/__init__.py
bob/learn/pytorch/utils.py
bob/learn/pytorch/architectures/CASIANet.py
bob/learn/pytorch/architectures/CNN8.py
bob/learn/pytorch/architectures/ConditionalGAN.py
bob/learn/pytorch/architectures/ConvAutoencoder.py
bob/learn/pytorch/architectures/DCGAN.py
bob/learn/pytorch/architectures/DeepMSPAD.py
bob/learn/pytorch/architectures/DeepPixBiS.py
bob/learn/pytorch/architectures/DltResNet.py
bob/learn/pytorch/architectures/FASNet.py
bob/learn/pytorch/architectures/LightCNN.py
bob/learn/pytorch/architectures/MCCNN.py
bob/learn/pytorch/architectures/MCCNNv2.py
bob/learn/pytorch/architectures/MCDeepPixBiS.py
bob/learn/pytorch/architectures/ResNet.py
bob/learn/pytorch/architectures/__init__.py
bob/learn/pytorch/architectures/utils.py
bob/learn/pytorch/datasets/__init__.py
bob/learn/pytorch/datasets/casia_webface.py
bob/learn/pytorch/datasets/data_folder.py
bob/learn/pytorch/datasets/data_folder_generic.py
bob/learn/pytorch/datasets/fargo.py
bob/learn/pytorch/datasets/multipie.py
bob/learn/pytorch/datasets/utils.py
bob/learn/pytorch/extractor/__init__.py
bob/learn/pytorch/extractor/audio/DummyExtractor.py
bob/learn/pytorch/extractor/audio/__init__.py
bob/learn/pytorch/extractor/image/DeepPixBiS.py
bob/learn/pytorch/extractor/image/FASNet.py
bob/learn/pytorch/extractor/image/LightCNN29.py
bob/learn/pytorch/extractor/image/LightCNN29v2.py
bob/learn/pytorch/extractor/image/LightCNN9.py
bob/learn/pytorch/extractor/image/MCCNN.py
bob/learn/pytorch/extractor/image/MCCNNv2.py
bob/learn/pytorch/extractor/image/MCDeepPixBiS.py
bob/learn/pytorch/extractor/image/__init__.py
bob/learn/pytorch/preprocessor/__init__.py
bob/learn/pytorch/preprocessor/audio/DltResNet.py
bob/learn/pytorch/preprocessor/audio/__init__.py
bob/learn/pytorch/scripts/__init__.py
bob/learn/pytorch/scripts/train_cnn.py
