Metadata-Version: 1.1
Name: bob.learn.pytorch
Version: 0.2.0
Summary: Bob bindings for PyTorch
Home-page: https://gitlab.idiap.ch/bob/bob.learn.pytorch
Author: Guillaume Heusch
Author-email: guillaume.heusch@idiap.ch
License: BSD
Keywords: pytorch
Platform: UNKNOWN
Classifier: Framework :: Bob
Classifier: Development Status :: 3 - Alpha
Classifier: Intended Audience :: Developers
Classifier: License :: OSI Approved :: GNU General Public License v3 (GPLv3)
Classifier: Natural Language :: English
Classifier: Programming Language :: Python
Classifier: Topic :: Scientific/Engineering :: Artificial Intelligence
